modeler/ImagePair.py
modeler/Matcher.py
modeler/PLY_Manip.py
modeler/PointCloudTable.py
modeler/SfM.py
modeler/SpacePoint.py
modeler/Triangulation.py
modeler/VideoToImages.py
modeler/__init__.py
modeler-0.0.1.dist-info/LICENSE
modeler-0.0.1.dist-info/METADATA
modeler-0.0.1.dist-info/WHEEL
modeler-0.0.1.dist-info/top_level.txt
modeler-0.0.1.dist-info/RECORD
