Metadata-Version: 2.1
Name: modeler
Version: 0.0.1
Summary: Reconstruct 3D models of objects from multiple images
Home-page: https://github.com/Wajdy759/modeler
Author: Wajdy
Author-email: itswajdy@gmail.com
License: mit
Platform: UNKNOWN
